devind_notifications/__init__.py
devind_notifications/apps.py
devind_notifications/helpers/__init__.py
devind_notifications/helpers/dispatch/__init__.py
devind_notifications/helpers/dispatch/base_dispatch.py
devind_notifications/helpers/dispatch/email_dispatch.py
devind_notifications/helpers/dispatch/telegram_dispatch.py
devind_notifications/management/seed/001.django_celery_beat/001.CrontabSchedule.json
devind_notifications/management/seed/001.django_celery_beat/002.PeriodicTask.json
devind_notifications/migrations/0001_initial.py
devind_notifications/migrations/0002_auto_20220401_1155.py
devind_notifications/migrations/0003_auto_20220404_2124.py
devind_notifications/migrations/__init__.py
devind_notifications/models/__init__.py
devind_notifications/models/mailing.py
devind_notifications/models/notification.py
devind_notifications/permissions/__init__.py
devind_notifications/permissions/notice_permissions.py
devind_notifications/permissions/notification_permissions.py
devind_notifications/schema/__init__.py
devind_notifications/schema/interfaces.py
devind_notifications/schema/mutations/__init__.py
devind_notifications/schema/mutations/notice_mutations.py
devind_notifications/schema/mutations/notification_mutations.py
devind_notifications/schema/subscriptions/__init__.py
devind_notifications/schema/subscriptions/notification_subscription.py
devind_notifications/schema/types.py
devind_notifications/settings.py
devind_notifications/signals.py
devind_notifications/tasks/__init__.py
devind_notifications/tasks/congratulation_tasks.py
devind_notifications/tasks/mail_tasks.py
devind_notifications/tasks/notification_tasks.py
devind_notifications/tests.py
devind_notifications-0.4.2.dist-info/LICENSE
devind_notifications-0.4.2.dist-info/WHEEL
devind_notifications-0.4.2.dist-info/METADATA
devind_notifications-0.4.2.dist-info/RECORD
